ckiptagger/__init__.py
ckiptagger/api.py
ckiptagger/data_utils.py
ckiptagger/model_ner.py
ckiptagger/model_pos.py
ckiptagger/model_ws.py
ckiptagger-0.3.0.dist-info/licenses/LICENSE
ckiptagger-0.3.0.dist-info/METADATA
ckiptagger-0.3.0.dist-info/WHEEL
ckiptagger-0.3.0.dist-info/top_level.txt
ckiptagger-0.3.0.dist-info/RECORD
