Metadata-Version: 2.4
Name: ckiptagger
Version: 0.3.0
Summary: Neural implementation of CKIP WS, POS, NER tools
Author-email: Li Peng-Hsuan <jacobvsdanniel@gmail.com>
License-Expression: GPL-3.0-only
Project-URL: Homepage, https://github.com/ckiplab/ckiptagger
Classifier: Programming Language :: Python :: 3
Classifier: Operating System :: OS Independent
Requires-Python: >=3.6
License-File: LICENSE
Requires-Dist: tf_keras
Requires-Dist: gdown
Dynamic: license-file
